blankly/__init__.py
blankly/__main__.py
blankly/enums.py
blankly/data/__init__.py
blankly/data/data_reader.py
blankly/data/templates/__init__.py
blankly/data/templates/keyless.py
blankly/data/templates/none.py
blankly/data/templates/none_screener.py
blankly/data/templates/rsi_bot.py
blankly/data/templates/rsi_screener.py
blankly/deployment/__init__.py
blankly/deployment/api.py
blankly/deployment/cli.py
blankly/deployment/deploy.py
blankly/deployment/exchange_data.py
blankly/deployment/keys.py
blankly/deployment/login.py
blankly/deployment/new_cli.py
blankly/deployment/reporter_headers.py
blankly/deployment/ui.py
blankly/exchanges/__init__.py
blankly/exchanges/abc_base_exchange.py
blankly/exchanges/abc_exchange.py
blankly/exchanges/abc_exchange_websocket.py
blankly/exchanges/exchange.py
blankly/exchanges/strategy_logger.py
blankly/exchanges/auth/__init__.py
blankly/exchanges/auth/auth_constructor.py
blankly/exchanges/auth/utils.py
blankly/exchanges/futures/__init__.py
blankly/exchanges/futures/futures_exchange.py
blankly/exchanges/futures/futures_strategy_logger.py
blankly/exchanges/interfaces/__init__.py
blankly/exchanges/interfaces/abc_base_exchange_interface.py
blankly/exchanges/interfaces/abc_exchange_interface.py
blankly/exchanges/interfaces/exchange_interface.py
blankly/exchanges/interfaces/futures_exchange_interface.py
blankly/exchanges/interfaces/websocket.py
blankly/exchanges/interfaces/alpaca/__init__.py
blankly/exchanges/interfaces/alpaca/alpaca.py
blankly/exchanges/interfaces/alpaca/alpaca_api.py
blankly/exchanges/interfaces/alpaca/alpaca_interface.py
blankly/exchanges/interfaces/alpaca/alpaca_websocket.py
blankly/exchanges/interfaces/alpaca/alpaca_websocket_utils.py
blankly/exchanges/interfaces/binance/__init__.py
blankly/exchanges/interfaces/binance/binance.py
blankly/exchanges/interfaces/binance/binance_api.py
blankly/exchanges/interfaces/binance/binance_interface.py
blankly/exchanges/interfaces/binance/binance_websocket.py
blankly-1.18.3b0.dist-info/LICENSE
blankly-1.18.3b0.dist-info/METADATA
blankly-1.18.3b0.dist-info/WHEEL
blankly-1.18.3b0.dist-info/entry_points.txt
blankly-1.18.3b0.dist-info/top_level.txt
blankly-1.18.3b0.dist-info/RECORD
