Metadata-Version: 2.1
Name: blankly
Version: 1.18.3b0
Summary: Rapidly build, backtest & deploy trading bots
Home-page: https://github.com/Blankly-Finance/Blankly
Author: blankly
Author-email: contact@blankly.finance
License: lgpl-3.0
Keywords: Crypto,Stocks,Quantitative Finance,Exchanges,Bot
Classifier: Development Status :: 4 - Beta
Classifier: Intended Audience :: Developers
Classifier: Intended Audience :: Financial and Insurance Industry
Classifier: License :: OSI Approved :: GNU Lesser General Public License v3 (LGPLv3)
Classifier: Programming Language :: Python :: 3.7
Classifier: Programming Language :: Python :: 3.8
Classifier: Programming Language :: Python :: 3.9
Classifier: Programming Language :: Python :: 3.10
License-File: LICENSE
Requires-Dist: questionary (>=1.10.0)
Requires-Dist: yaspin (>=2.1.0)
Requires-Dist: alpaca-trade-api (>=1.4.2)
Requires-Dist: bokeh (>=2.4.2)
Requires-Dist: dateparser (>=1.1.0)
Requires-Dist: newnewtulipy (>=0.4.6.3)
Requires-Dist: numpy (>=1.21.4)
Requires-Dist: pandas (>=1.1.5)
Requires-Dist: python-binance (>=1.0.15)
Requires-Dist: requests (>=2.26.0)
Requires-Dist: websocket-client (>=1.2.1)
